eventsail.py
eventsail-0.1.2.dist-info/METADATA
eventsail-0.1.2.dist-info/WHEEL
eventsail-0.1.2.dist-info/RECORD
